picept/__init__.py
picept/context.py
picept/init.py
picept/tracing/__init__.py
picept/tracing/decorators.py
picept/tracing/tracer.py
picept-0.1.1.dist-info/METADATA
picept-0.1.1.dist-info/WHEEL
picept-0.1.1.dist-info/top_level.txt
picept-0.1.1.dist-info/RECORD
